<WA council="1">
<RESOLUTION><CATEGORY>Repeal</CATEGORY>
<COAUTHOR>
<N>lanias</N>
</COAUTHOR>
<CREATED>1760456445</CREATED>
<DESC><![CDATA[The World Assembly,

[i]Acknowledging[/i] the intent behind GA#709 to protect WA employees, dismissed or active, identifiers, and merits issued by the WA from unlawful exploitation;

[i]Confused[/i] why the prohibition on misrepresentation only extends to those with the intent to harm others and ignores those with other intentions, or those with the sole intent to benefit the individual;

[i]Believing[/i] that the World Assembly is an international body whose symbols belong to no specific member;

[i]Concerned[/i] about the excessiveness of trademarking all WA UI in all member and non-member states with a trademarking program;

[i]Understanding[/i] that while trademarking may serve as a tool to limit misrepresentation of the WA, in certain jurisdictions including non-member states which are not bound by extant WA resolutions, it will restrict freedom of expression and art;

[i]Alarmed[/i] that non member-states have access to registers regarding WA Personnel, as defined in the target resolution, without the same rigorous &#147;need to know basis&#148; requirements established for member-states;

Hereby repeals GA#709 &#147;WA Misrepresentation Protocols&#148;.]]></DESC>
<ID>moduland_1760456445</ID>
<NAME>Repeal &quot;WA Misrepresentation Protocols&quot;</NAME>
<OPTION>1198</OPTION>
<PROMOTED>1767718803</PROMOTED>
<PROPOSED_BY>moduland</PROPOSED_BY>
<TOTAL_NATIONS_AGAINST>403</TOTAL_NATIONS_AGAINST>
<TOTAL_NATIONS_FOR>2026</TOTAL_NATIONS_FOR>
<TOTAL_VOTES_AGAINST>1321</TOTAL_VOTES_AGAINST>
<TOTAL_VOTES_FOR>6734</TOTAL_VOTES_FOR>
<VOTES_AGAINST><N>cinnamoroll_city</N>
<N>kevin3</N>
<N>new_bacalao_and_the_aurora_islands</N>
<N>zivloka</N>
<N>ortandemhausergebautwerden</N>
<N>bessarasia</N>
<N>hurlania</N>
<N>celtayoshi</N>
<N>west_silverland</N>
<N>communist-denmark</N>
<N>the_grand_snake_empire</N>
<N>free_ganalia</N>
<N>vurk</N>
<N>bolian_island</N>
<N>knootoss</N>
<N>screwballia</N>
<N>new_yankmoth</N>
<N>modernity_survivors</N>
<N>ivn</N>
<N>fomahault</N>
<N>democracylandistan</N>
<N>eieryn</N>
<N>szurea</N>
<N>euskadil</N>
<N>goberno_do_lago</N>
<N>archonexus</N>
<N>germania_ultima_4</N>
<N>ostschleife</N>
<N>differences-in-differences</N>
<N>inner_mations_aststan</N>
<N>kyubia</N>
<N>non-believers</N>
<N>st_scarlett</N>
<N>blobular</N>
<N>new_angus</N>
<N>dicko</N>
<N>bobraqia</N>
<N>andech</N>
<N>revolutionary_anarchy</N>
<N>determination_users</N>
<N>logorio</N>
<N>clvesthurah</N>
<N>wolfhawk</N>
<N>varangiana</N>
<N>dzhongkha</N>
<N>the_tree_states</N>
<N>edo-prussia</N>
<N>itani</N>
<N>jorovia</N>
<N>socialist_america_sa</N>
<N>the_greatest_proletariat</N>
<N>the_sinistress</N>
<N>forio</N>
<N>everywheristan</N>
<N>shan_nation</N>
<N>centauri_republican_state</N>
<N>filipino_north_carolina</N>
<N>the_holy_baptist_church</N>
<N>philosopy</N>
<N>argylia</N>
<N>king_zhaoxiang_of_qin</N>
<N>simone_republic</N>
<N>skwar</N>
<N>iona-ropa</N>
<N>razdor</N>
<N>chemung</N>
<N>antontia</N>
<N>the_great_comrades_of_the_revolution</N>
<N>rusticus_damianus</N>
<N>slavonia_and_srijem</N>
<N>kalmykhia</N>
<N>non_sequitur</N>
<N>deepsea</N>
<N>calicov</N>
<N>kisume_the_bucket_youkai</N>
<N>redwood_bureau</N>
<N>virange_ii</N>
<N>the_prosperous_coast</N>
<N>namante</N>
<N>omnitech</N>
<N>gibbervoln</N>
<N>amerion</N>
<N>ballotonia</N>
<N>shanaka</N>
<N>benicarlo</N>
<N>frantion</N>
<N>aina_kuokoa</N>
<N>the_great_slime_nation_of_nick</N>
<N>almonaster_nuevo</N>
<N>blueberry_islands</N>
<N>karelianastan</N>
<N>avalonium</N>
<N>no_vadi</N>
<N>eastoria</N>
<N>tumberu</N>
<N>kanoshu</N>
<N>sao-paulo</N>
<N>brunyxia</N>
<N>western_yakutsk</N>
<N>malaguetia</N>
<N>upper_got</N>
<N>the_islamic_khilafah</N>
<N>alf_landon</N>
<N>ibarabayashi</N>
<N>digi_cube</N>
<N>mapperdonia</N>
<N>kwaj</N>
<N>wakandiania</N>
<N>arthropyria</N>
<N>sweaboo_land</N>
<N>fickland2</N>
<N>saarland-westpalia</N>
<N>santa_saber</N>
<N>santi_nadu</N>
<N>hilagang_bituin</N>
<N>amorana</N>
<N>terran_england</N>
<N>adinesi</N>
<N>hong_kong_kowloon_and_new_territories</N>
<N>jamesburgh</N>
<N>archshaven</N>
<N>anglischland_kaiserreich</N>
<N>der_weimar_republik</N>
<N>kingdom_of_urus</N>
<N>umeria</N>
<N>dun_frest</N>
<N>dossec_hills</N>
<N>voxija</N>
<N>ajton</N>
<N>hartward</N>
<N>draconic_aiur</N>
<N>imperium_anglorum</N>
<N>mania_sims</N>
<N>khavvkhnsjnjiekh</N>
<N>tryienne</N>
<N>sovietland</N>
<N>the_states_of_ashkanza</N>
<N>volaworand</N>
<N>pays_cathare</N>
<N>alaskan_free_state1</N>
<N>wutar_katari</N>
<N>lillitheve</N>
<N>nowa_europa</N>
<N>ponta_tropical</N>
<N>fiery_hell_hole</N>
<N>anthropoelpis</N>
<N>industric</N>
<N>ebonhand</N>
<N>solisian_union</N>
<N>the_workers_united</N>
<N>great_borelia</N>
<N>latviju</N>
<N>titanaria</N>
<N>umns_iznikmid</N>
<N>stafftopia</N>
<N>ginnara</N>
<N>moodova</N>
<N>jamnagar</N>
<N>the_dolein</N>
<N>stragiland</N>
<N>promax</N>
<N>north_verulas</N>
<N>trumpiff</N>
<N>mirea</N>
<N>behh</N>
<N>amazon_states</N>
<N>citycity</N>
<N>new_scratchiland</N>
<N>ilhas_san_ricardo</N>
<N>wilkshire</N>
<N>tellotictacious_whindlewharf</N>
<N>herfenzir</N>
<N>summerset_sea</N>
<N>kindjal</N>
<N>solarampa</N>
<N>united_cattania</N>
<N>amexipania</N>
<N>luxize</N>
<N>wallanda</N>
<N>aegartha</N>
<N>sporaltryus</N>
<N>kunigsrrock</N>
<N>the_ferret_lands</N>
<N>woorth_sectiaistan</N>
<N>the_offical_jungle_isle_of_neverway</N>
<N>mintermanicule</N>
<N>tana_grocea</N>
<N>violent_hatred</N>
<N>leouschburgh</N>
<N>mendevia</N>
<N>untermite</N>
<N>the_soviet_states_of_europe</N>
<N>zocra</N>
<N>aethernum</N>
<N>popolar_soviet_republics_of_novogradia</N>
<N>gmt2001</N>
<N>melenchonia</N>
<N>free_socialist_republik_of_novastovia</N>
<N>malaya_communism</N>
<N>soriana</N>
<N>raghallaigh</N>
<N>proletariatit</N>
<N>ballaria</N>
<N>bingleborpia</N>
<N>lake_worth</N>
<N>merijnteren_empire</N>
<N>minafederal</N>
<N>icarema</N>
<N>larsovania</N>
<N>poram_companies</N>
<N>anuadh</N>
<N>requand</N>
<N>peopir</N>
<N>nuremgard</N>
<N>vargstad</N>
<N>respidon</N>
<N>rokatov</N>
<N>northevia</N>
<N>warzakie</N>
<N>new_maxta</N>
<N>naragia</N>
<N>bayfront</N>
<N>nacupopej</N>
<N>arscanesia</N>
<N>saxxony</N>
<N>escotiaa</N>
<N>starenia</N>
<N>new_land_of_cats</N>
<N>kaiyrzgsyzstan</N>
<N>greater_liverpool</N>
<N>impreo_de_jap</N>
<N>apellidor</N>
<N>hesker</N>
<N>europe_or_eur</N>
<N>communal_socialist_republics</N>
<N>kluchassia</N>
<N>swanson_grove</N>
<N>valkyrie_reborn</N>
<N>ammmericaaaa</N>
<N>new-ferytland</N>
<N>touisterland</N>
<N>mayroba_and_the_constantines</N>
<N>pretty_boy</N>
<N>saint_cobia_sitzer</N>
<N>sakobell</N>
<N>artamisiland</N>
<N>intaglio</N>
<N>the_polar_reigons</N>
<N>kolketi</N>
<N>anuriv</N>
<N>azzata</N>
<N>hearteland</N>
<N>manila-central</N>
<N>skaladoria</N>
<N>the_continental_north_pole</N>
<N>farmcraft</N>
<N>the_authority_of_the_underwater_cities</N>
<N>bluejam</N>
<N>shiverian_republics</N>
<N>weitzel</N>
<N>eastern_octechokofnatsses</N>
<N>deluolu</N>
<N>alangrad</N>
<N>nezgzarp</N>
<N>lytaran</N>
<N>regnum_italiae</N>
<N>last_outer_heaven</N>
<N>islaremistan</N>
<N>old_jeresy</N>
<N>statosnat</N>
<N>timao</N>
<N>her_malue</N>
<N>sullaan</N>
<N>haunover</N>
<N>schitz</N>
<N>tsuskia</N>
<N>allwarts</N>
<N>elverhoy</N>
<N>random_island_in_the_arctic</N>
<N>blappen</N>
<N>equability</N>
<N>velke</N>
<N>himurajima</N>
<N>aguyje-yvy</N>
<N>aruvenai</N>
<N>paradise_and_zion</N>
<N>yardies</N>
<N>wohabutu</N>
<N>dugalena</N>
<N>lixonia</N>
<N>niolex</N>
<N>madjack</N>
<N>groussherzogtumletzebuerg</N>
<N>goatvillia</N>
<N>inner_ted_imazahvatia</N>
<N>topo</N>
<N>the_test</N>
<N>nonfredom</N>
<N>fox_anthro_of_germany</N>
<N>belladonnia</N>
<N>volksrepubliek_belgie</N>
<N>mulaonia</N>
<N>daneka</N>
<N>the_doa</N>
<N>sanana</N>
<N>dessambra</N>
<N>tushto</N>
<N>regalitaria</N>
<N>erstavik</N>
<N>i_lick_pig</N>
<N>maverick</N>
<N>timbolandi</N>
<N>christian_killeshandra</N>
<N>novaignis</N>
<N>lipaland</N>
<N>eyluvmenia</N>
<N>vardanyia</N>
<N>carolignie</N>
<N>new_napoleon</N>
<N>ferrianona</N>
<N>leptimora</N>
<N>grace_wellesley_thayer</N>
<N>atlantic_ocean_and_its_tributaries</N>
<N>quta</N>
<N>refugeeria</N>
<N>novist</N>
<N>stata_pontificia</N>
<N>vulgustan</N>
<N>alstratzkon</N>
<N>pruani</N>
<N>united_kolotarces</N>
<N>democratic_prichiaordia</N>
<N>pulitein</N>
<N>zutroy</N>
<N>petronellania</N>
<N>england_1</N>
<N>di_mentago</N>
<N>hellenic_socialist_union</N>
<N>tyuiopia_2</N>
<N>jobinia</N>
<N>pindorama-brasil</N>
<N>movovia</N>
<N>wattsland</N>
<N>arcti-chan</N>
<N>dulroth</N>
<N>biaten</N>
<N>northern_slatavia</N>
<N>new_vladislavia</N>
<N>gorena</N>
<N>nesslandia</N>
<N>new_salty</N>
<N>new_scottika</N>
<N>chippan</N>
<N>waffia</N>
<N>nomaur</N>
<N>anarres_ii</N>
<N>cuteachtsland</N>
<N>cow_hunters</N>
<N>szentia</N>
<N>pepsi_the_third</N>
<N>shadownia</N>
<N>sfa</N>
<N>servitronia</N>
<N>buran_energia</N>
<N>the_soviet_state_of_svalbard</N>
<N>socialist_balkan_states</N>
<N>genesis_fifteen</N>
<N>aus_straya</N>
<N>pansnews</N>
<N>hanalia</N>
<N>mavenu</N>
<N>vennos</N>
<N>eledras</N>
<N>the_legionarian_isles</N>
<N>viltrum_1</N>
<N>rhenna</N>
<N>northwest_north_america</N>
<N>grand_wisteria</N>
<N>socialist_hercegovina</N>
<N>nova_elisio</N>
<N>fransmany</N>
<N>the_forish</N>
<N>jzonim</N>
<N>riandera</N>
<N>northern_michael-land</N>
<N>pantumaca</N>
<N>cliyf_drines</N>
<N>soem</N>
<N>kazimeriz</N>
<N>nova_loca</N>
<N>olarista</N>
<N>very_new_republic_of_madinia</N>
<N>nortallius</N>
<N>arozodi</N>
<N>aumest</N>
<N>cute_pandas</N>
<N>neo_mikolania</N>
<N>kanitoria</N>
<N>gender_rolls</N>
<N>nullhia</N>
<N>al_abamistan</N>
<N>libertineparis</N>
<N>vendonesiam</N></VOTES_AGAINST>
<VOTES_FOR><N>tokora</N>
<N>tingo_lep_hex</N>
<N>phoronu</N>
<N>etlajhia</N>
<N>creberg</N>
<N>crnagorska</N>
<N>autonomous_cascadia</N>
<N>darkanistan</N>
<N>curlyhoward</N>
<N>daulmark</N>
<N>college_corner</N>
<N>new_holy_rome</N>
<N>nacion_nation_5</N>
<N>polleend</N>
<N>united_socialist_islands_of_aerospatiala</N>
<N>syaftyn</N>
<N>azuriaaa</N>
<N>warkus</N>
<N>mecren</N>
<N>andy67</N>
<N>falceverdi</N>
<N>bhang_bhang_duc</N>
<N>glaciertop</N>
<N>-leon</N>
<N>rayneia</N>
<N>shuckletopia</N>
<N>arolaun</N>
<N>tttbtr</N>
<N>arnheimia</N>
<N>southeast_celebes</N>
<N>illestan</N>
<N>calabo</N>
<N>magnaformia</N>
<N>the_neomasonic_gay_liberal_soros_state</N>
<N>tsardom_of_zimnyaya</N>
<N>harperians</N>
<N>eka</N>
<N>cantuss</N>
<N>united_nations_expeditionary_forces</N>
<N>mishikeland</N>
<N>santynelio</N>
<N>golinistan</N>
<N>independent_principalities</N>
<N>eclil</N>
<N>formenore</N>
<N>cfdu1202</N>
<N>vulpencia</N>
<N>a3161</N>
<N>gumeus</N>
<N>nagakara</N>
<N>dimension_of_planets</N>
<N>talsien</N>
<N>vaizar</N>
<N>new_charles</N>
<N>xizertan</N>
<N>itsebed</N>
<N>rhoboeria</N>
<N>soruli</N>
<N>tasman_empire</N>
<N>new_bradfordsburg</N>
<N>korotis</N>
<N>volkind</N>
<N>grec_ridde</N>
<N>west_alria</N>
<N>ordria</N>
<N>west_strangeland</N>
<N>the_scandinavian_realm</N>
<N>discgolfland</N>
<N>arqadiya</N>
<N>latvian_state</N>
<N>sol_lycopersi</N>
<N>janakin</N>
<N>gagium</N>
<N>free_state_of_lokix</N>
<N>sumina</N>
<N>slobodovia</N>
<N>deeznuts5</N>
<N>bkakc</N>
<N>dutch_states_and_territories</N>
<N>twisted_duality</N>
<N>kineaux</N>
<N>da_chunghwa</N>
<N>dark_chaos_insurgency</N>
<N>piglinlandia</N>
<N>hypany</N>
<N>akross</N>
<N>theurgia</N>
<N>the_great_empire_of_europe_ii</N>
<N>dixie_florida</N>
<N>philipinesdw</N>
<N>geeked_vs_locked_in</N>
<N>northern_ost_samenia</N>
<N>ossaiville67</N>
<N>tanpendecuaro</N>
<N>kepteal</N>
<N>turrimos</N>
<N>talentiert</N>
<N>zaharial</N>
<N>greater_portugaliza</N>
<N>luxdiei</N>
<N>chalistine</N>
<N>holy_cascadian_imperium</N>
<N>sonbeira</N>
<N>actualidad</N>
<N>memestw</N>
<N>nazar_amulet</N>
<N>inaros_opa</N>
<N>new_fredoenia</N>
<N>humanix</N>
<N>stanvrin</N>
<N>funnle_kake</N>
<N>raskana</N>
<N>the_great_states_of_mexico</N>
<N>reberydinigzadaland</N>
<N>hibernia_kaas</N>
<N>alski</N>
<N>wisterian_kaiserreich</N>
<N>biggonian_megaist_empire</N>
<N>astriloquia</N>
<N>oceanic_ai_of_arctic_ocean</N>
<N>mesvice</N>
<N>marvaro</N>
<N>mercuwury</N>
<N>florindale</N>
<N>fund_of_the_king</N>
<N>dbastion</N>
<N>bostro</N>
<N>aradache</N>
<N>redbaronia</N>
<N>kebecois</N>
<N>azerrat</N>
<N>roman_american</N>
<N>estados_socialistas_unidos_de_iberia</N>
<N>vanna_tallinn</N>
<N>oswaldtheluckyrabbit</N>
<N>revachol-</N>
<N>thx1138</N>
<N>matsabie</N>
<N>junastria</N>
<N>we_hate_our_people</N>
<N>virksland</N>
<N>awesome_lesbianland</N>
<N>iremia</N>
<N>southern_elbonia</N>
<N>aukeland</N>
<N>helcretia</N>
<N>itinchlumdan</N>
<N>najovio</N>
<N>united_anarchist_state_of_ukraine</N>
<N>factoristan</N>
<N>veln</N>
<N>the_unified_purview</N>
<N>moukden_and_kirin</N>
<N>crimsongbt</N>
<N>eaetafershe</N>
<N>svarteyjar</N>
<N>dustwind</N>
<N>therashcangs</N>
<N>anarchist_states_of_africa</N>
<N>indonasianana</N>
<N>king_of_urbino</N>
<N>xunira</N>
<N>denorsweland</N>
<N>jaydee_ii</N>
<N>slaca</N>
<N>nordmarck</N>
<N>indesputatio</N>
<N>ardu</N>
<N>vitorianiania</N>
<N>the_ruby_court</N>
<N>nalver_and</N>
<N>rhodevus</N>
<N>zemisnorth_technologies_ltd</N>
<N>azure_normandy</N>
<N>dest_oritio</N>
<N>gitchie_manito</N>
<N>bracadun</N>
<N>carasca</N>
<N>madrapustum</N>
<N>popcorn_north_dakota</N>
<N>steium</N>
<N>tuhreland</N>
<N>rendom</N>
<N>falernesia</N>
<N>riotania</N>
<N>micomania</N>
<N>elklan</N>
<N>wesian</N>
<N>puttysborough</N>
<N>obeseblobia</N>
<N>gladeffland5</N>
<N>united_estland</N>
<N>kehudia</N>
<N>silverpaw69</N>
<N>tera_stellarum</N>
<N>singamadri</N>
<N>austriax</N>
<N>nordiv</N>
<N>jliang</N>
<N>nevala</N>
<N>kilpatricka</N>
<N>united_countries_of_north_america</N>
<N>the_empire_of_alerba</N>
<N>eserenya</N>
<N>eragon_island</N>
<N>the_red_cross</N>
<N>friaritat</N>
<N>prestonland</N>
<N>heletica</N>
<N>cheeseburrito</N>
<N>east_thule</N>
<N>nuttywood</N>
<N>estados_socialistas_independentes</N>
<N>the_real_underground</N>
<N>little_evansville</N>
<N>caerinthus</N>
<N>rev_aria</N>
<N>ingentus_progressia</N>
<N>farbelia</N>
<N>digital_drovakia</N>
<N>rusozak</N>
<N>aweentitante</N>
<N>hopia_owl</N>
<N>omnistria</N>
<N>new_aequalitas</N>
<N>mongolz</N>
<N>ikkerus</N>
<N>lfe</N>
<N>floaquia</N>
<N>stratocratic-anarchy_oceanic_empire</N>
<N>aguacada</N>
<N>the_yiddish</N>
<N>alto_ipiranga</N>
<N>maritzal</N>
<N>detroitsmash</N>
<N>lurusitania</N>
<N>rocknesse</N>
<N>vobron</N>
<N>the_patriotic_republic_of_kosovo</N>
<N>aigania</N>
<N>the_southern_great_lakes</N>
<N>vulkanshire</N>
<N>marxist_land_of_peoples</N>
<N>vuvuvia</N>
<N>lunaeri</N>
<N>petrostan</N>
<N>sapnupuas</N>
<N>the_tro_zimoub_islands</N>
<N>states_of_eastern_america</N>
<N>pacific_federation_company</N>
<N>neue_albania</N>
<N>the_chill_union</N>
<N>policka</N>
<N>the_grand_alliance_of_goons</N>
<N>forfishing</N>
<N>ismstein</N>
<N>xithino</N>
<N>soviet_yoshilandia</N>
<N>montagway</N>
<N>meadowfields</N>
<N>anakeion</N>
<N>rechol</N>
<N>windurst</N>
<N>stal_valley</N>
<N>neoxona</N>
<N>my_holiness</N>
<N>dominion_of_dinguses</N>
<N>lost_bananamen</N>
<N>kazackhistan</N>
<N>the_technocratic_authority</N>
<N>the_union_of_ibistic_states</N>
<N>the_shaymen</N>
<N>marocimia</N>
<N>the_island_of_kaamos</N>
<N>deims_kir</N>
<N>altanor</N>
<N>cadonio</N>
<N>zt333</N>
<N>hundskol</N>
<N>ardemar</N>
<N>gandieland</N>
<N>romaniki_aftokratoria</N>
<N>danjou</N>
<N>united_beherbia</N>
<N>keith_emerson</N>
<N>technocratic_great_lakes</N>
<N>edenaria</N>
<N>fat_angel</N>
<N>faxtroot</N>
<N>bronchial_forest</N>
<N>floofith</N>
<N>x_country</N>
<N>higgstonia</N>
<N>shreken</N>
<N>the_free_republic_of_the_people</N>
<N>nova_aohr</N>
<N>spartaaa</N>
<N>duetcha</N>
<N>onomanatopoeia</N>
<N>wintra</N>
<N>the_rhein_federation</N>
<N>ervald</N>
<N>narvatus</N>
<N>east_moon_colony</N>
<N>pultorland</N>
<N>criboutit</N>
<N>suburbistanistan</N>
<N>alterra_corporations</N>
<N>palognia</N>
<N>murderos</N>
<N>new_vipa</N>
<N>mallatrovia</N>
<N>lightford</N>
<N>the_dark_aether</N>
<N>alsion</N>
<N>ruztips</N>
<N>all_creation</N>
<N>basvelantia</N>
<N>russila</N>
<N>el_hierro</N>
<N>shimutoji</N>
<N>tokau</N>
<N>klopptopolis</N>
<N>phoidoss</N>
<N>possum_lakes</N>
<N>tepertopia</N>
<N>pakitsk</N>
<N>nationbest1</N>
<N>new_new_zachland</N>
<N>uguru</N>
<N>drasene</N>
<N>thyrall</N>
<N>socialist_world_order</N>
<N>blorpshire</N>
<N>thaporeal_iv</N>
<N>the_swiftest_warriors</N>
<N>synaire</N>
<N>libertas_minor</N>
<N>mightaria</N>
<N>pazamor</N>
<N>russian_archangelsk</N>
<N>tetoslavya</N>
<N>scot_blan_kin</N>
<N>badger</N>
<N>the_windmilluminati</N>
<N>vylixan</N>
<N>greater_agnolia</N>
<N>new_crywyzyxycynya</N>
<N>sumeru_meru</N>
<N>varien</N>
<N>bronzehamut</N>
<N>ninsianna</N>
<N>republic_of_taehyang</N>
<N>clantonia</N>
<N>sorealand</N>
<N>bexsomb</N>
<N>draico</N>
<N>new_pigeonia</N>
<N>halsoni</N>
<N>pantoslavia</N>
<N>el_grenitadia</N>
<N>urcea</N>
<N>the_c_o_r_r_u_p_t_union</N>
<N>quasi-stellar_star_civilizations</N>
<N>zeu</N>
<N>berthlandia</N>
<N>wakeopolis</N>
<N>ataraesh</N>
<N>ostermark_prussia</N>
<N>detroit_pro_max_ai</N>
<N>yunmei</N>
<N>united_states_of_alpha</N>
<N>the_socialist_federation_nord_machadonia</N>
<N>rhodeesland</N>
<N>kezh</N>
<N>alfolin</N>
<N>inner_laucesse</N>
<N>president_hassan_rouhani</N>
<N>oyggj_skye</N>
<N>big_pennieginnieginnie</N>
<N>prosopon</N>
<N>krestasrijh</N>
<N>dalosa</N>
<N>the_nation_of_quinn</N>
<N>andso_mangis</N>
<N>free_maduro</N>
<N>emellgosakeriasalimiadewa</N>
<N>kingdom_of_kasiopea</N>
<N>ankviet</N>
<N>koulointopia</N>
<N>uteda</N>
<N>the_discipled</N>
<N>zhs0715</N>
<N>dytase</N>
<N>the_solace_corperation</N>
<N>maravina</N>
<N>kent_valley</N>
<N>south-antartic</N>
<N>khijovia</N>
<N>aurasreich</N>
<N>novele_anjou</N>
<N>norvoria</N>
<N>crossvegas</N>
<N>aethyrcadia</N>
<N>money_and_not_happiness</N>
<N>tiranat</N>
<N>sol_occidens</N>
<N>russian_united_federation</N>
<N>gambling_addictions</N>
<N>lenias</N>
<N>irtho_paul</N>
<N>aryoti</N>
<N>idinist_imauggland</N>
<N>an_si</N>
<N>yashastan</N>
<N>the_sun_on_rise</N>
<N>heritagela</N>
<N>ghojingles</N>
<N>lotanio</N>
<N>rovska</N>
<N>kond_mex_ethostorgel</N>
<N>skedia</N>
<N>thomas_harriot</N>
<N>imperii_feminam</N>
<N>east_regalian</N>
<N>lycanion</N>
<N>kyrek</N>
<N>moduland</N>
<N>hiloooooo</N>
<N>hufficanarty</N>
<N>druznia</N>
<N>wickedly_evil_people</N>
<N>zintai</N>
<N>nami_no_kuni</N>
<N>myra_nortan</N>
<N>imperial_saber</N>
<N>arghadia</N>
<N>fendera</N>
<N>setnei</N>
<N>drawkland</N>
<N>weveto</N>
<N>brando</N>
<N>chalybea</N>
<N>korbalis</N>
<N>scyldaria</N>
<N>autonomous_unified_territories</N>
<N>samsarastan</N>
<N>united_bongo_states_of_the_new_america</N>
<N>brightwalden</N>
<N>sigumastan</N>
<N>dodsworthia</N>
<N>capibara_countrey</N>
<N>lucas_island</N>
<N>europeasia</N>
<N>rook_fjord</N>
<N>halverton</N>
<N>steinbaun</N>
<N>alestadpolkhbizzydor</N>
<N>oaooeooioouoyoomonov</N>
<N>yukti</N>
<N>hornmoguelesland</N>
<N>the_mansi</N>
<N>arvek</N>
<N>prussia_republican_kingdom</N>
<N>mundus_novia</N>
<N>north_bratislava</N>
<N>cromulent_peoples</N>
<N>mayadere</N>
<N>edupetkhah</N>
<N>current_british_colony</N>
<N>japan2662</N>
<N>feng_shui_dictatoriat</N>
<N>giggles_empire</N>
<N>nova_renascentia</N>
<N>thelandoffunfunfun</N>
<N>new_ice1and</N>
<N>ghurlan</N>
<N>ekreli</N>
<N>zynax</N>
<N>los_santos</N>
<N>xoshya</N>
<N>republiostan</N>
<N>lanias</N>
<N>sphrantzes</N>
<N>ichirokuhachi</N>
<N>asterst</N>
<N>the_united_crogalian_nations</N>
<N>the_rico_re_ah_republic</N>
<N>militaires_san_frontieres</N>
<N>metropolitinville</N>
<N>guanabaraea</N>
<N>alder_alderaan</N>
<N>fractalnavel</N>
<N>valcour_island</N>
<N>wellassona</N>
<N>soriguana</N>
<N>ranover</N>
<N>suzi_island</N>
<N>eretzora</N>
<N>the_crusader_kings</N>
<N>pelagon</N>
<N>new_kashubia</N>
<N>le_libertia</N>
<N>union_kingdoms</N>
<N>the_socialist_republic_of_columbia</N>
<N>coopera_social</N>
<N>unsophisticate</N>
<N>acrotraria</N>
<N>trerio</N>
<N>domesticis</N>
<N>ubani</N>
<N>rosethrone</N>
<N>orasil</N>
<N>tugana</N>
<N>astle_gua</N>
<N>commie_celadio</N>
<N>do_brasil_da_america</N>
<N>finlayndia</N>
<N>rockolandia</N>
<N>jaspertown</N>
<N>armorian_union</N>
<N>filipino_union</N>
<N>terrabis-seran</N>
<N>ilocandia-cagayan</N>
<N>gastravon</N>
<N>avaerilon</N>
<N>baldorium</N>
<N>nieuweland</N>
<N>new_garbanzia</N>
<N>stormwallis</N>
<N>kimjonilia</N>
<N>kusarrian_union</N>
<N>free_stalliongrad</N>
<N>cunamas</N>
<N>the_way_sun_cooperation</N>
<N>the_united_patagonian_states</N>
<N>dyl</N>
<N>israel_emirates</N>
<N>alta_castria</N>
<N>novauria</N>
<N>tavok</N>
<N>kosanhask</N>
<N>yaronia</N>
<N>new_xyon</N>
<N>cansne</N>
<N>parzillum</N>
<N>cameronia_excellentia</N>
<N>ancarchyland</N>
<N>imperial_catorianis</N>
<N>oscealia</N>
<N>palmerstone</N>
<N>lightning4004</N>
<N>bankowiata</N>
<N>franny4land</N>
<N>great_britain_and_the_isles</N>
<N>great_barvaria</N>
<N>atralasia</N>
<N>bengalines</N>
<N>the_terren_dominion</N>
<N>arcadiaaa</N>
<N>loorpkin</N>
<N>new_vedlar</N>
<N>doumeira</N>
<N>ballzia</N>
<N>girkublown</N>
<N>zenobiana</N>
<N>walter_jackson</N>
<N>felornis</N>
<N>faralried</N>
<N>vikarion</N>
<N>dravastan</N>
<N>zalann</N>
<N>saccurania</N>
<N>vlandaria</N>
<N>ostio</N>
<N>thosularia</N>
<N>canbrasouth</N>
<N>the_balken_federation</N>
<N>east_catlandia</N>
<N>die_eusan</N>
<N>poiseidonia</N>
<N>baltree</N>
<N>new_liella</N>
<N>bralru</N>
<N>amsden</N>
<N>fiparatus</N>
<N>isda</N>
<N>masters86</N>
<N>casarian</N>
<N>serenitium</N>
<N>glynnova</N>
<N>fadnesia</N>
<N>eashavist</N>
<N>the_persian_territories</N>
<N>marvel_jesus</N>
<N>paradalvia</N>
<N>wesmont</N>
<N>mcdonaldland5</N>
<N>waisnor</N>
<N>uni_nova_terra</N>
<N>cola_peninsula</N>
<N>the_free_birds</N>
<N>someseni</N>
<N>demonmania</N>
<N>arstotskiano</N>
<N>staffon</N>
<N>jammlandia</N>
<N>hayfielda</N>
<N>lilli_lands</N>
<N>dragon_isles</N>
<N>oceasia</N>
<N>samund_facobs</N>
<N>dark_alps</N>
<N>nukerida</N>
<N>palermitus</N>
<N>xanaxh</N>
<N>druvenia</N>
<N>kornovia</N>
<N>greater_britannian_realm</N>
<N>republica_k0</N>
<N>pokemanland</N>
<N>jithago</N>
<N>gelassenheit</N>
<N>electric_koto</N>
<N>tokoral</N>
<N>manuelian_empire</N>
<N>ruatar</N>
<N>effazio</N>
<N>neopunk-brazil</N>
<N>democratic_republic_of_animeo</N>
<N>hyperion_prime</N>
<N>kelvaros_prime</N>
<N>cerdenian_states</N>
<N>the_starian_people</N>
<N>gladius_scutum</N>
<N>tinhampton</N>
<N>dingusville2</N>
<N>new_samon</N>
<N>devirah</N>
<N>vaii</N>
<N>sal_vikoland</N>
<N>scottrick</N>
<N>muad-dib</N>
<N>pichu23</N>
<N>hendersonia</N>
<N>landbang_rkipo_islands</N>
<N>radiant_rolly_pollys</N>
<N>yy4u</N>
<N>southern_maus</N>
<N>raccland</N>
<N>salairat</N>
<N>neptunian_military_administration</N>
<N>trichechuse</N>
<N>rebel-topia</N>
<N>surne</N>
<N>troc</N>
<N>caladonne</N>
<N>shibutani</N>
<N>whald</N>
<N>karai_nadu</N>
<N>ruaun</N>
<N>didt</N>
<N>malchata</N>
<N>buddharma</N>
<N>willow_gate</N>
<N>yessir_town</N>
<N>islands_cottonish</N>
<N>renanland</N>
<N>north_westsylvania</N>
<N>bangea</N>
<N>mondstadtes_kaisereich</N>
<N>americanican</N>
<N>hobura</N>
<N>terranica_states</N>
<N>the_united_neptumousian_empire</N>
<N>theocratic_conservistan</N>
<N>matika</N>
<N>covenentia</N>
<N>salterra</N>
<N>uueidhhd</N>
<N>bavo</N>
<N>syrtic</N>
<N>frontiera</N>
<N>sowerval</N>
<N>hearthmere</N>
<N>united_socialist_states_of_the_ussr</N>
<N>serum_ete_onlonia</N>
<N>skibmidi</N>
<N>northern_zorbrasnka</N>
<N>the_cerulean_nation</N>
<N>rein_delossinarryomi</N>
<N>northern_synntest_tounouste</N>
<N>cypheri</N>
<N>immanuel_college</N>
<N>no_freedoom</N>
<N>perditions_reach</N>
<N>memememe-</N>
<N>von_mor</N>
<N>0000001</N>
<N>humanian_free_state</N>
<N>zevvelbourg</N>
<N>wilhelmsstadt</N>
<N>alam_melayu</N>
<N>czarskovia</N>
<N>the_other_margaret</N>
<N>rio_de_arkansas</N>
<N>the_solid_members</N>
<N>mosclavy</N>
<N>afifray</N>
<N>smithican4</N>
<N>kurzbestonn</N>
<N>edgerladraysteanoust</N>
<N>burntpeanutgoop</N>
<N>sinderwood</N>
<N>nova_danzig</N>
<N>free_planets_allience</N>
<N>hashishin</N>
<N>greater_deutsche</N>
<N>ramajana</N>
<N>the_shadow_fold</N>
<N>enlil</N>
<N>texel_and_vlieland</N>
<N>nas_crustium</N>
<N>soviet_federative_socialists</N>
<N>hashidi</N>
<N>tsertle_of_turtle</N>
<N>roxanda</N>
<N>canton_empire</N>
<N>nilrem</N>
<N>elwher</N>
<N>los_enquirers</N>
<N>schwazerland</N>
<N>akrapat</N>
<N>san_angelina</N>
<N>kinanland</N>
<N>catcom</N>
<N>hinomia</N>
<N>sekantar</N>
<N>puglanda</N>
<N>great_will_millennium</N>
<N>dignic_freuraternia</N>
<N>aranaya</N>
<N>cutias</N>
<N>wangano</N>
<N>the_trilla_gang_mafia</N>
<N>birczia</N>
<N>sankt-adalbertian_states</N>
<N>west_almsworth</N>
<N>lebronraymonejamesdagoat</N>
<N>great_utopian_states</N>
<N>vatrello</N>
<N>frismana</N>
<N>hellolandia</N>
<N>eloscape</N>
<N>arucaria</N>
<N>republic_of_suharto</N>
<N>new_arbuckle</N>
<N>inner_ryxtylopia</N>
<N>olyndor</N>
<N>bai_lung</N>
<N>workuta_thob</N>
<N>ataraxian_mainframe</N>
<N>hueyhueyhuey</N>
<N>republic_of_bludia</N>
<N>federative_empire</N>
<N>the_poor_peoples_republic</N>
<N>the_peoples_place_of_living</N>
<N>yoresteria</N>
<N>the_black_isles</N>
<N>zorkinthia</N>
<N>good_eatin</N>
<N>aexalta</N>
<N>croshov_union</N>
<N>vulcan_persons</N>
<N>bonzium</N>
<N>cherry_limeade</N>
<N>hunterdon</N>
<N>the_nightmare_and_dreams</N>
<N>untied_coulee_state</N>
<N>billyism</N>
<N>elyaria</N>
<N>saperetia</N>
<N>majoritania</N>
<N>treadwellia</N>
<N>mjau</N>
<N>the_talisman</N>
<N>sotam</N>
<N>tokuto</N>
<N>esteneng</N>
<N>godmodia</N>
<N>republic_of_aspen</N>
<N>geneseean</N>
<N>chip_skylark</N>
<N>second_kitary</N>
<N>kornapan</N>
<N>of_the_golden_harp</N>
<N>usaint</N>
<N>beanastan</N>
<N>wasd12</N>
<N>united_okticand</N>
<N>-eunomia</N>
<N>tir_gaelach</N>
<N>marcula</N>
<N>verithlana</N>
<N>srius</N>
<N>the_union_of_costa_rica</N>
<N>mechanocracy</N>
<N>maracay_2030</N>
<N>losaita</N>
<N>ourdenia</N>
<N>legio_x_vercingetorix_of_deutschland</N>
<N>nederlandse_staat</N>
<N>penguin_imperium</N>
<N>poolanxi</N>
<N>fauconberg</N>
<N>serpleddyland</N>
<N>borkmaster</N>
<N>scotsgale</N>
<N>ghad</N>
<N>the_champions_league</N>
<N>cookie_crumbia</N>
<N>durmengrad_prime</N>
<N>eeveetopila</N>
<N>ne-kotikas</N>
<N>lukaficarth</N>
<N>histarctica</N>
<N>7agyeisia</N>
<N>the_gamers_of_roblox</N>
<N>individuality_is_bad</N>
<N>orioni_2</N>
<N>gryphonne</N>
<N>the_western_european_commonwealth</N>
<N>planetmercury</N>
<N>madhonia</N>
<N>the_capitalist_reich_of_sigmatown</N>
<N>radgaov</N>
<N>kyaksbel</N>
<N>the_astora_empire</N>
<N>crazy_firemen</N>
<N>al-nayir</N>
<N>the_puppet_state_of_mercury</N>
<N>femvania</N>
<N>true_china-</N>
<N>ashkenazi_regime</N>
<N>saint-luccania</N>
<N>tradila</N>
<N>union_of_anarchist_territories</N>
<N>klatonia</N>
<N>envoi2</N>
<N>clarest</N>
<N>lucy_the_hell</N>
<N>tiglias</N>
<N>quesbia</N>
<N>dramancass</N>
<N>holy_marcus_empire</N>
<N>grand_eden</N>
<N>isachile_tum</N>
<N>prismette</N>
<N>thehouseofsilly</N>
<N>inevitable_poverty</N>
<N>berlitria</N>
<N>felid_robloxia</N>
<N>kanashia</N>
<N>capridam</N>
<N>valerion</N>
<N>marquestan</N>
<N>bergiervile</N>
<N>the_pillow_labyrinth</N>
<N>the_republic_of_antartica</N>
<N>battadia</N>
<N>hisenna</N>
<N>loveable_dogs</N>
<N>theonic_empire</N>
<N>sommath</N>
<N>yaztopia</N>
<N>treekidistan</N>
<N>ble_ble</N>
<N>geezy_for_life</N>
<N>cedaronia</N>
<N>the_new_midlands</N>
<N>dirmia</N>
<N>noeland2</N>
<N>maraffe</N>
<N>socialist_republic_of_australia</N>
<N>aeravia</N>
<N>foxy</N>
<N>eastamgriumirkialand</N>
<N>los_camellos</N>
<N>xiggor</N>
<N>sardinavia</N>
<N>ein_sof</N>
<N>tomikals</N>
<N>basaroa</N>
<N>frosthafen</N>
<N>norwegian_forest_cat</N>
<N>armeriea</N>
<N>free_massachusetts</N>
<N>helvard</N>
<N>the_malaysian_tamil_nadu</N>
<N>subhamnation</N>
<N>san_pellegrino_romana</N>
<N>new_ecania</N>
<N>pumpkin_valley</N>
<N>east_avalon</N>
<N>guteinitast</N>
<N>huijuo</N>
<N>jacobopolus</N>
<N>south_isaactopia</N>
<N>beddia</N>
<N>stickofark</N>
<N>the_crow_collectors</N>
<N>niederlande-preussen</N>
<N>scrumpleville</N>
<N>ziemgale</N>
<N>creator_land</N>
<N>chotana</N>
<N>andoran_empire</N>
<N>free_turtle</N>
<N>garamantia</N>
<N>clano_rigin</N>
<N>deonicia</N>
<N>quegantordia</N>
<N>imperial_prores_hydriterian</N>
<N>darkmania</N>
<N>his_immortal_dictator_joseph</N>
<N>serenvale</N>
<N>lamandica</N>
<N>kthedummy</N>
<N>aurora_mirai</N>
<N>socialist_xlyvania</N>
<N>rhaza</N>
<N>somburg</N>
<N>ventusky</N>
<N>graysoap</N>
<N>blazefire2</N>
<N>jaegerpondonia</N>
<N>nergtul</N>
<N>ethanstewartopia4</N>
<N>skynidos</N>
<N>hylia</N>
<N>naterraleh_priais</N>
<N>arbialand</N>
<N>bahalbha_island</N>
<N>bicdic</N>
<N>kasekyl</N>
<N>varisland</N>
<N>clarinatia</N>
<N>azzarel</N>
<N>zeppekash</N>
<N>new_alkrias</N>
<N>communist_new_island</N>
<N>redwingvksm</N>
<N>grod_island</N>
<N>gig_em_aggies</N>
<N>arwad</N>
<N>melanie_long</N>
<N>rainbow_sunset</N>
<N>sackballs</N>
<N>escaragua</N>
<N>flaxland</N>
<N>yahragot</N>
<N>mazunda</N>
<N>klanda</N>
<N>magrusa</N>
<N>convaria</N>
<N>allstardeni</N>
<N>ophaesia</N>
<N>jc_jenson</N>
<N>thegoldenempiregermany</N>
<N>serenitas_novae</N>
<N>sirius_zenith</N>
<N>karenus</N>
<N>maverique</N>
<N>valcouria</N>
<N>nayara</N>
<N>democracia_de_portugal</N>
<N>bulgaria-russia</N>
<N>ratateague</N>
<N>amphorus</N>
<N>tarligean</N>
<N>the_ancient_world</N>
<N>polish_west_slavia</N>
<N>america_samoa_territory</N>
<N>romerduh</N>
<N>gustavia_indaia</N>
<N>hyetnam</N>
<N>vimaran</N>
<N>land_without_shrimp</N>
<N>gay_maryland</N>
<N>weltbeherrschung</N>
<N>coswoto</N>
<N>bakhuchistan</N>
<N>st_jose</N>
<N>krykalin</N>
<N>bandivia</N>
<N>gallus</N>
<N>gobania</N>
<N>innovaris</N>
<N>satreburg_2</N>
<N>dark-type_eeveelution</N>
<N>sheppy_the_king</N>
<N>the_united_canadian_provinces</N>
<N>hong_wan</N>
<N>multiple_bounty</N>
<N>csaland</N>
<N>rosie_bee</N>
<N>grabahan</N>
<N>vitezos</N>
<N>nilesnia</N>
<N>queen_jane_grey</N>
<N>haymarket_riot</N>
<N>giri_kedhaton</N>
<N>dorpatia2</N>
<N>cretox_state</N>
<N>zumrudqislaq</N>
<N>scandaland</N>
<N>alexein</N>
<N>gendirt</N>
<N>republiciana</N>
<N>medvefold</N>
<N>far_isles</N>
<N>soletmaris</N>
<N>ultimategooner</N>
<N>the_flanders</N>
<N>decimus_maximus</N>
<N>chukstik_illahi</N>
<N>tzechni</N>
<N>wyrdas</N>
<N>narav</N>
<N>lopsided_goat</N>
<N>the_lost_lost_states</N>
<N>west_domotrica</N>
<N>upc</N>
<N>orgation_ii</N>
<N>smurfey</N>
<N>greater_bay</N>
<N>terrane</N>
<N>gathadia</N>
<N>germany-georgia</N>
<N>zavea</N>
<N>istuvia</N>
<N>unified-korea</N>
<N>demou_catanz</N>
<N>shuora</N>
<N>parrots_den</N>
<N>new_kalve</N>
<N>cambany</N>
<N>the_royal_asmorian_federation</N>
<N>francanada</N>
<N>glyjb</N>
<N>krute_empire</N>
<N>sutland_rep</N>
<N>the_concord_republic</N>
<N>zalzastan</N>
<N>duista</N>
<N>holy_empire_of_armenia</N>
<N>grenzhia-ghrostvina</N>
<N>vormiar</N>
<N>lastovipol</N>
<N>alesina</N>
<N>118_elements</N>
<N>vandermeer</N>
<N>dacarbatia</N>
<N>ummah_al-majid</N>
<N>bireek</N>
<N>haporlynkia</N>
<N>xialta</N>
<N>foixla</N>
<N>yadablow</N>
<N>xyuqur</N>
<N>theroria</N>
<N>angusessa</N>
<N>anatolia_londo</N>
<N>lakesideia</N>
<N>the_pharaohship</N>
<N>atteang</N>
<N>freidonia_empire</N>
<N>ariner</N>
<N>newest_foundedland</N>
<N>wilhelms_reich</N>
<N>taw93</N>
<N>naronya</N>
<N>takiv</N>
<N>corfad</N>
<N>satukland</N>
<N>antara</N>
<N>united_republic_of_manland</N>
<N>dionysian</N>
<N>markanista</N>
<N>lascandra</N>
<N>the_portuguese_workers</N>
<N>grand-turinia</N>
<N>united_venkat</N>
<N>zanphil</N>
<N>art_landia</N>
<N>kongeraich_ostpruisen</N>
<N>sohaib</N>
<N>nova_earth</N>
<N>lovateria</N>
<N>kyrgyzstanistan</N>
<N>pipi_pampers</N>
<N>the_royal_republic_of_kumania</N>
<N>darlingsvania6</N>
<N>caporika</N>
<N>sozland</N>
<N>haxxland</N>
<N>sanctum_teriaris</N>
<N>socialist_republic_of_russians</N>
<N>los_vasion</N>
<N>taginvia</N>
<N>neutrinostan</N>
<N>esquieia</N>
<N>robo_topia</N>
<N>foraldn</N>
<N>north_sion</N>
<N>great_britain-and_northern_ireland</N>
<N>norwegian_democratic_republic</N>
<N>disneylandia</N>
<N>estellan</N>
<N>axelotl</N>
<N>toriski</N>
<N>the_states_of_turkmenitsan</N>
<N>the_holy_principality_of_saint_mark</N>
<N>sefat</N>
<N>kabran</N>
<N>aveune_nation</N>
<N>tavalia</N>
<N>the_republic_of_worldia</N>
<N>the_communist_soviet_of_india</N>
<N>pranassa</N>
<N>the_havaikians</N>
<N>bjornifjordaland</N>
<N>lizard_antifascism_unit</N>
<N>mcdonalds0</N>
<N>rasutafia</N>
<N>crintopria</N>
<N>itanland</N>
<N>libertarian_washington</N>
<N>futuo</N>
<N>the_immortal_fire_nation</N>
<N>fated</N>
<N>aquelistan</N>
<N>agima</N>
<N>communal_commonality</N>
<N>penning</N>
<N>famockadia_jel</N>
<N>british_goreoyo</N>
<N>zombiedolphins</N>
<N>hergasst</N>
<N>united_states_federal_government</N>
<N>empire_of_new_lemon</N>
<N>nalenua</N>
<N>libersan</N>
<N>dem_undine</N>
<N>southern_folising_euctandered</N>
<N>scotriana</N>
<N>aerlinth</N>
<N>boboni</N>
<N>slothville</N>
<N>columbiqash</N>
<N>zepub_sollenticityia</N>
<N>aze_shrouxia</N>
<N>dombaness</N>
<N>turanids</N>
<N>germanicreich</N>
<N>stiliyan</N>
<N>the_gates_of_delirium</N>
<N>republic_of_priouthia</N>
<N>drupec</N>
<N>igarion</N>
<N>cinarhaven</N>
<N>the_cevanti_free_council</N>
<N>affonea</N>
<N>island_of_catland</N>
<N>western_arba_fir</N>
<N>westinghous</N>
<N>mediobogdum</N>
<N>lemordo</N>
<N>urgandi</N>
<N>yungerdash</N>
<N>velenia</N>
<N>jaxonedia</N>
<N>titanan</N>
<N>yodle</N>
<N>new_deathland</N>
<N>dancest</N>
<N>vinlandist</N>
<N>impallia</N>
<N>sedgistan</N>
<N>genetic_labs_inc</N>
<N>lantheia</N>
<N>noxvolkia</N>
<N>the_augustans</N>
<N>stareogratia</N>
<N>sackostan</N>
<N>luminality</N>
<N>pryskiva</N>
<N>brendon</N>
<N>stotecia</N>
<N>murica_squared</N>
<N>eastern_christania</N>
<N>neo_american_states</N>
<N>the_union_of_the_people_of_britannia</N>
<N>anctraziania</N>
<N>nikosias</N>
<N>splena</N>
<N>chambaneser</N>
<N>foderales_konigreich_schlesien</N>
<N>charlaton</N>
<N>lancashia</N>
<N>warokkia</N>
<N>krematoria</N>
<N>vanuzgard</N>
<N>basiloria</N>
<N>thebyes</N>
<N>transhalva</N>
<N>democratic_chanum_ter_heak</N>
<N>xtralandia</N>
<N>echothesis</N>
<N>serovgrad</N>
<N>kingdom_of_tincart</N>
<N>volcanor</N>
<N>sunny_glade</N>
<N>greaine</N>
<N>saulterlan</N>
<N>the_coolest_kids</N>
<N>blancovia</N>
<N>dizera_ouriadiab</N>
<N>the_new_ganges</N>
<N>poppy_dadas</N>
<N>aeryn</N>
<N>phigosa</N>
<N>ronaldan</N>
<N>new_kisha</N>
<N>neo_imperial_america</N>
<N>the_habsburgian_dietslands</N>
<N>merantang_kota</N>
<N>euricanis</N>
<N>braustrina</N>
<N>the_philippine_islands_and_formosa</N>
<N>at-m6</N>
<N>zesole</N>
<N>narmarsia</N>
<N>super_nice_people</N>
<N>rynoth</N>
<N>the_marxist_state</N>
<N>annakendrickland</N>
<N>kingdom_of_east_russia</N>
<N>sia_movanzan</N>
<N>ekopia</N>
<N>new_listenbourg</N>
<N>the_grand_republic_of_mystikpolem</N>
<N>xhennovia</N>
<N>killiani</N>
<N>the_texas_lone_star_republic</N>
<N>the_bronze_star</N>
<N>koda-land</N>
<N>ilbira</N>
<N>york_zionia</N>
<N>french_new_wake_island</N>
<N>marxist-leninist_russian_federation</N>
<N>damaskia</N>
<N>havenwelle</N>
<N>covant</N>
<N>sciuridae</N>
<N>the_og_your_moms_mom</N>
<N>vazcoeur</N>
<N>unitacee</N>
<N>fallowat</N>
<N>skjoldenmark</N>
<N>the_dovahkiin_caliphate</N>
<N>gargmani</N>
<N>moon_deing</N>
<N>kyrindor_puppet</N>
<N>liberty_martyred_wa</N>
<N>new_fernia</N>
<N>rodpia</N>
<N>cera_dova</N>
<N>arenac</N>
<N>eme_andorland</N>
<N>great_of_han</N>
<N>roberto_garcia</N>
<N>south_merkopa</N>
<N>new_athens_republic</N>
<N>wagner_group_pmc</N>
<N>hen_ogledd</N>
<N>atethat</N>
<N>suave</N>
<N>lovarpia</N>
<N>queephe_debal</N>
<N>alupo</N>
<N>new_cali_republic</N>
<N>densaner</N>
<N>chillin</N>
<N>doge_flower</N>
<N>mororo</N>
<N>iketon</N>
<N>szovlk</N>
<N>vicotis_kor</N>
<N>grande_guanabara</N>
<N>krzyzewskiville</N>
<N>hileville</N>
<N>ueclaya</N>
<N>republic_of_ablakistan</N>
<N>exteda</N>
<N>popoli_liberi</N>
<N>the_fox_kingdom</N>
<N>brilish</N>
<N>foritehland</N>
<N>kannae</N>
<N>nova_imperial</N>
<N>alphus_imperium</N>
<N>the_eastern_coast</N>
<N>nelenkorp</N>
<N>voopmont</N>
<N>mirahge</N>
<N>humsawy</N>
<N>malenkia</N>
<N>astol</N>
<N>honduhn</N>
<N>kaiserburgia</N>
<N>potenzia</N>
<N>solaryia</N>
<N>rhinosport</N>
<N>ambarinadino</N>
<N>aina_pomaikai</N>
<N>new_nator</N>
<N>cordani</N>
<N>demeter</N>
<N>galindo_prime</N>
<N>le_kartoffel</N>
<N>worlanythorg</N>
<N>asukalia</N>
<N>konzhov</N>
<N>la_xinga</N>
<N>doux_belsh</N>
<N>cruciland</N>
<N>mornangren</N>
<N>apexlald</N>
<N>quendor</N>
<N>angmash_easter</N>
<N>trillius</N>
<N>vancovaria</N>
<N>freystan</N>
<N>burg_land</N>
<N>asahimachi</N>
<N>old_new_ravensburg</N>
<N>malotihuacan</N>
<N>r_h_o_m_a_n_i_a</N>
<N>draconian-empire</N>
<N>mestaths_ghoin</N>
<N>kharakhovistan</N>
<N>h-zhena</N>
<N>araragistan</N>
<N>sauros</N>
<N>new_frencia</N>
<N>portugal_empire_state</N>
<N>abhyuday</N>
<N>the_limean_islands</N>
<N>astra_prime</N>
<N>valknord</N>
<N>the_washington_federation</N>
<N>guanxigun</N>
<N>smimismi</N>
<N>jjustice</N>
<N>united_red_soviets</N>
<N>beal_an_mhuirthead</N>
<N>zimera</N>
<N>centralsk</N>
<N>republic_polos</N>
<N>noobbia</N>
<N>issime</N>
<N>azflebrigan</N>
<N>khrelowda</N>
<N>lesvo</N>
<N>united_states_of_philipdelphia</N>
<N>castuna</N>
<N>koragrad</N>
<N>gods_promised_land</N>
<N>cyvin</N>
<N>castelia</N>
<N>solotaca</N>
<N>hellslayer</N>
<N>conconedes</N>
<N>playmobilandia_del_este</N>
<N>burning_pants</N>
<N>urlaska</N>
<N>imperial_british_state</N>
<N>new_butchart</N>
<N>the_unified_soviet_union</N>
<N>dengist_china</N>
<N>holy_catheria</N>
<N>pellinor</N>
<N>humanlonia</N>
<N>socialist_red_league</N>
<N>velisila_ljudstva</N>
<N>1jax0</N>
<N>orpheia</N>
<N>auraesia</N>
<N>nurdia</N>
<N>tikikey</N>
<N>novaportugalidade</N>
<N>the_royal_hussars</N>
<N>united_republic_of_the_south_east</N>
<N>gideon</N>
<N>dryhtenland</N>
<N>nagakawa</N>
<N>the_beelands</N>
<N>yoshisha</N>
<N>ohga_bohga_unga</N>
<N>neoxoleria</N>
<N>heristal_raposhystru</N>
<N>father_ursidae</N>
<N>the_ghol</N>
<N>randomly_generated_technology</N>
<N>mejor_estado</N>
<N>united_music_nation</N>
<N>greythorne</N>
<N>fortovia</N>
<N>state_democratic_assembly</N>
<N>schokoladeinderschublade</N>
<N>infusvia</N>
<N>nymany</N>
<N>magnitka</N>
<N>rawatna</N>
<N>claysville</N>
<N>isualia</N>
<N>araschravia</N>
<N>saphman</N>
<N>democratic_wer</N>
<N>leuzinger</N>
<N>kaliuvat</N>
<N>norvokorr</N>
<N>hellasiea</N>
<N>second_peenadian</N>
<N>neugania</N>
<N>sultanate_of_mindanao</N>
<N>aryo_diningrat</N>
<N>new_england_inc</N>
<N>fallgriffin</N>
<N>endless_summer_2</N>
<N>general_tn</N>
<N>bavarian_soviet_repulic</N>
<N>tareqiyyah</N>
<N>tripod_ii</N>
<N>kriegsreich_of_iron</N>
<N>asriellia</N>
<N>maariko</N>
<N>loutsland</N>
<N>shady_gun_dealers</N>
<N>hopslia</N>
<N>oktotheio</N>
<N>united_holiness_lands</N>
<N>ineva</N>
<N>sudoeste</N>
<N>creedsible</N>
<N>dolayasia</N>
<N>tunghoang</N>
<N>crozland</N>
<N>tiodann</N>
<N>god_the_father_son_and_holy_spirit</N>
<N>bursken</N>
<N>sashilee</N>
<N>island_zero</N>
<N>ubergaffen</N>
<N>nova_britannia_merchant_company</N>
<N>fava_wes_nemo</N>
<N>fortic</N>
<N>novacore_dynamics</N>
<N>manaslu</N>
<N>cyberpunk_nation</N>
<N>blakalandia</N>
<N>zuuri</N>
<N>portburg</N>
<N>cornelia</N>
<N>guymondium</N>
<N>triumvirate_of_euphoria</N>
<N>the_armed_union</N>
<N>buedafixe</N>
<N>skelleftella</N>
<N>phlontopia</N>
<N>the_skull_federation</N>
<N>slembana</N>
<N>albaenia</N>
<N>the_oldest_dream</N>
<N>mhmea</N>
<N>the_drifting_deity</N>
<N>zac_not_zach</N>
<N>the_united_corporate_commonwealth</N>
<N>perdura</N>
<N>grod_dratia</N>
<N>serrus</N>
<N>outer_higonica_armyevillyp</N>
<N>prolitaria</N>
<N>boredistan</N>
<N>sierracastillo2</N>
<N>moryazvia</N>
<N>chioganah</N>
<N>the_chosen_souls</N>
<N>anglost</N>
<N>sonilandia</N>
<N>united_territori</N>
<N>falloa</N>
<N>argondy</N>
<N>hasaeng</N>
<N>blandowia</N>
<N>xylenia_adfor</N>
<N>rosettan_overwatch</N>
<N>eight_mile_bay</N>
<N>imperium_corporativum_romanum</N>
<N>honeymoon_avenue</N>
<N>the_hurricane</N>
<N>picairn</N>
<N>the_cold_country</N>
<N>greenvi</N>
<N>demon_girl</N>
<N>oseao</N>
<N>saint_barks-webados</N>
<N>fragevereyland</N>
<N>the_freebird</N>
<N>osimiria</N>
<N>arcriea</N>
<N>goatseania</N>
<N>newer_ostland</N>
<N>holy_byzantine</N>
<N>braddos</N>
<N>novo_prosperitas</N>
<N>akunzoian_empire</N>
<N>eryaurt</N>
<N>great_minwas</N>
<N>mutan</N>
<N>paskaa</N>
<N>yaniolia</N>
<N>malalonius</N>
<N>the_florida_national_front</N>
<N>norvarxilaland</N>
<N>gran_azuria</N>
<N>northern_caliburugeve</N>
<N>west_ferris</N>
<N>grand_technate_of_the_new_world</N>
<N>farville</N>
<N>bingobongos</N>
<N>the_ecalpan_uchuugun</N>
<N>yuskovsk</N>
<N>furballland</N>
<N>farello</N>
<N>xenetaria</N>
<N>urziksthan</N>
<N>nethervale</N>
<N>cyberia_prime</N>
<N>claibornia</N>
<N>ewing_oil_co</N>
<N>sanctified_hellas</N>
<N>king_rankmore</N>
<N>geastia</N>
<N>palaubania</N>
<N>seraia_and_the_xiaides</N>
<N>the_turtles</N>
<N>adkissa</N>
<N>salvagard-huston</N>
<N>dhomhnaigh</N>
<N>zantiom</N>
<N>commonu</N>
<N>old_atlantica</N>
<N>semper-luxuria</N>
<N>varanius</N>
<N>oztil</N>
<N>new_bubastis</N>
<N>sararia</N>
<N>the_chaffinches</N>
<N>eusvan</N>
<N>pand_alp</N>
<N>calank</N>
<N>konigsreich_von_prussen</N>
<N>fairigone</N>
<N>squishville</N>
<N>communardia</N>
<N>pen_blanityion</N>
<N>arcomo</N>
<N>the_west_united_states</N>
<N>ajakor</N>
<N>milimuppet</N>
<N>the_dome</N>
<N>tritonitia</N>
<N>thuanu</N>
<N>galahad_avalonia</N>
<N>the_citrus_republic</N>
<N>the_new_islands_of_fredonia</N>
<N>aarden_nations</N>
<N>ingrosia</N>
<N>rio_de_mouro</N>
<N>the_hiyah_empire</N>
<N>tnp-ed</N>
<N>isle_ideal</N>
<N>draween</N>
<N>eggtowne</N>
<N>ekpatanus</N>
<N>morrie</N>
<N>reino_scarlatta</N>
<N>dootinbow</N>
<N>daynes</N>
<N>telaret</N>
<N>pakania</N>
<N>strogamehouf</N>
<N>kalendaa</N>
<N>gran_valor</N>
<N>pathonia</N>
<N>zugtok</N>
<N>sha_la_la_land</N>
<N>magna-parva</N>
<N>zlapadoslavia</N>
<N>fasan_venus</N>
<N>solinarien</N>
<N>plateana</N>
<N>oganing</N>
<N>iocrionia</N>
<N>crowncity</N>
<N>saxon-anglaland</N>
<N>nistriabar</N>
<N>libertarian_confederation_of_terranova</N>
<N>zinertia</N>
<N>scotana</N>
<N>atomicbomba</N>
<N>garvija</N>
<N>san_giuda</N>
<N>vostag</N>
<N>limboese</N>
<N>daggria</N>
<N>kaidan</N>
<N>the_iron_lions</N>
<N>protzastan_5</N>
<N>ethnon</N>
<N>bearstackof2015</N>
<N>dregs_of_the_earth</N>
<N>the_jaddari_legion</N>
<N>the_somme</N>
<N>morzova</N>
<N>castrolaysia</N>
<N>bazuka</N>
<N>ile_de_francia</N>
<N>liberza</N>
<N>theunitedrepublics_of_greaterscandinavia</N>
<N>new_old_fordlandia_2</N>
<N>xaeloa</N>
<N>lael_piotr</N>
<N>the_trianic_isolationists</N>
<N>nueva_alta_california</N>
<N>the_mahrou</N>
<N>tominos</N>
<N>aurn_atla_lars</N>
<N>the_modern_byzantine_union</N>
<N>snorlaxia</N>
<N>pekweng</N>
<N>ahren-glanzenden</N>
<N>7thutopiaofthapa</N>
<N>quetornia</N>
<N>troll_punishers</N>
<N>omynix</N>
<N>west_russia_republic</N>
<N>sik_gra</N>
<N>asinger</N>
<N>noobia_and_solare</N>
<N>uudam_tal</N>
<N>salleland</N>
<N>mockia</N>
<N>nagorathia</N>
<N>leaviatin</N>
<N>cogdelve</N>
<N>elliym</N>
<N>hamburg_neo</N>
<N>kadariyamania4</N>
<N>juelsborg</N>
<N>the_merinos</N>
<N>danilo</N>
<N>potato_gun</N>
<N>the_ussr_rebirth</N>
<N>amabilis</N>
<N>sovni-aguirre</N>
<N>islen_domatero</N>
<N>new_aquitaine</N>
<N>bizarrotan</N>
<N>cheeseniria</N>
<N>the_nation_of_doan</N>
<N>dexian</N>
<N>prackin_kelew</N>
<N>rust</N>
<N>concordare</N>
<N>valeania</N>
<N>erosodom</N>
<N>bessemeria</N>
<N>saintthebia</N>
<N>sovereign_state1</N>
<N>the_lide_collective</N>
<N>the_devskian_revolutionary_republic</N>
<N>loenay</N>
<N>skookiea</N>
<N>norcoast</N>
<N>freakbobland</N>
<N>kingdom_of_the_focke-wulf_islands</N>
<N>diyarbarkir</N>
<N>freedomstaki</N>
<N>courage_caverns</N>
<N>orksian</N>
<N>united_loyika_habalrium</N>
<N>arpioska</N>
<N>malkara</N>
<N>natit_vakkazi</N>
<N>the_dale_snatfoxy</N>
<N>ear_exploder_9000</N>
<N>jackpot_jackpot_jackpot_jackpot</N>
<N>nations_of_canzuk</N>
<N>st_saratoga</N>
<N>komyounists</N>
<N>the_vatican_town_of_csa</N>
<N>s2p1729</N>
<N>val_de_france</N>
<N>greater_nebraska</N>
<N>dennissee</N>
<N>haldeni</N>
<N>thinking_space_2</N>
<N>xid</N>
<N>carterthian3</N>
<N>ectovoid</N>
<N>eoksia</N>
<N>pygania</N>
<N>benlloch</N>
<N>comercia</N>
<N>nascadia</N>
<N>nizar_kindom</N>
<N>the_chezburger</N>
<N>mark</N>
<N>dark_soul</N>
<N>sun_wo_kong</N>
<N>something_random</N>
<N>tank_republicans</N>
<N>manseria</N>
<N>11_templar_knights</N>
<N>the_nation_of_nathan</N>
<N>kawany</N>
<N>nafoland</N>
<N>silberglanz</N>
<N>pekares</N>
<N>laws_and_bylaws</N>
<N>danishire</N>
<N>darklighters</N>
<N>wood_motherland</N>
<N>chavak</N>
<N>komodo_empire</N>
<N>dormill_and_stiura</N>
<N>new_found_america</N>
<N>arbados_balarascia</N>
<N>altanteean</N>
<N>rolooks</N>
<N>septentrica</N>
<N>yhudfg_khanate</N>
<N>chillicothe</N>
<N>the_new_global_order</N>
<N>white_noise</N>
<N>vichtander</N>
<N>coorvus</N>
<N>mildo_tuh</N>
<N>thiothard</N>
<N>venico</N>
<N>novin_wesimm</N>
<N>gardorthland</N>
<N>zarian</N>
<N>dynasty_ubangoh7</N>
<N>runderhale</N>
<N>reyalda</N>
<N>the_empire_of_orion</N>
<N>roylaii</N>
<N>maravell</N>
<N>separtia</N>
<N>the_republic_of_the_united_marble_tribes</N>
<N>rayeland</N>
<N>varnavia</N>
<N>kinglore7</N>
<N>netsach</N>
<N>liko</N>
<N>kirby-land</N>
<N>niehart</N>
<N>ardamion</N>
<N>harjad</N>
<N>nordurstjarna</N>
<N>enkhaltan</N>
<N>ciclope</N>
<N>anuahrfscdurbfced</N>
<N>isla_luminara</N>
<N>tomie</N>
<N>kimoia</N>
<N>democratic_therperiotto</N>
<N>trebizondia</N>
<N>plexaris</N>
<N>viretopia</N>
<N>urzine</N>
<N>yuyu</N>
<N>la_naval_de_manila</N>
<N>imperium_romae_marii</N>
<N>rkd</N>
<N>tystan</N>
<N>kralenos</N>
<N>wang_yao</N>
<N>shankland</N>
<N>the_grand_lucas_crusades</N>
<N>alinek</N>
<N>walkabout</N>
<N>triumphancy</N>
<N>kraj</N>
<N>new_del_rey</N>
<N>tir_rois</N>
<N>frosty_orbit</N>
<N>israelitan</N>
<N>maple_islands</N>
<N>scarlettjohansson</N>
<N>puraykinia</N>
<N>wolffoxia</N>
<N>dustinesia</N>
<N>automaton_collective</N>
<N>the_smoking_peanut</N>
<N>hellspire</N>
<N>cultlamb</N>
<N>southern_numenor</N>
<N>insiag</N>
<N>trombosnia_reborn</N>
<N>salinus</N>
<N>frozen_crown</N>
<N>aseanam</N>
<N>texas_attempt_2</N>
<N>mbok</N>
<N>glademont</N>
<N>broweth</N>
<N>lysset</N>
<N>hapam</N>
<N>chughtaiya</N>
<N>itilium</N>
<N>makaab</N>
<N>mission_tejas</N>
<N>the_state_of_baathist_iraq</N>
<N>oesterlund</N>
<N>adantine</N>
<N>new_jia</N>
<N>superb_order</N>
<N>kahlmardhani</N>
<N>szentfold</N>
<N>recentr</N>
<N>amestris-britannia</N>
<N>wilsertown26</N>
<N>eldwyn</N>
<N>molson_iceland</N>
<N>shachms</N>
<N>solar_energy_and_free_states</N>
<N>zunsettia</N>
<N>maximillion</N>
<N>woodsmere</N>
<N>badegg</N>
<N>knightfallia</N>
<N>san_toreno</N>
<N>lestasya</N>
<N>aegisfell</N>
<N>gates_was_right</N>
<N>ilyia</N>
<N>morwaldia</N>
<N>united_jacaria</N>
<N>sokiata</N>
<N>gothc</N>
<N>sakurielle</N>
<N>reformed_russian_states</N>
<N>bagojo</N>
<N>nepri</N>
<N>arlanda</N>
<N>amorise</N>
<N>senshu</N>
<N>samgreat</N>
<N>south_otselic</N>
<N>greater_atlantis</N>
<N>doggos1234</N>
<N>yugoslawia</N>
<N>anarborous</N>
<N>araunia</N>
<N>northern_german_federation</N>
<N>datalearner</N>
<N>despokeidus</N>
<N>third_indochina</N>
<N>detrona</N>
<N>united_independent_kingdoms</N>
<N>greater_charles</N>
<N>duga</N>
<N>the_central_islands</N>
<N>american_rojava</N>
<N>kurranulla</N>
<N>paradystopia</N>
<N>arsenial</N>
<N>fanauifo</N>
<N>romivia</N>
<N>bookment</N>
<N>veliki-yekaterinograd</N>
<N>tutels</N>
<N>european_socialist_councils</N>
<N>destials</N>
<N>malatoga</N>
<N>republica_federal_de_catalunya</N>
<N>vorenza</N>
<N>psychopantachy</N>
<N>sweway</N>
<N>sumran</N>
<N>prydaein</N>
<N>kukskladia</N>
<N>viperreich</N>
<N>dongming</N>
<N>northernloin</N>
<N>the_kingdom_of_rainier</N>
<N>sveniland</N>
<N>drachen</N>
<N>milkzorzistan</N>
<N>aaronian</N>
<N>gud</N>
<N>kelban_island</N>
<N>south_danzig</N>
<N>xcarca</N>
<N>gillespia5</N>
<N>woreyland</N>
<N>great_britain_and_ireland_ns</N>
<N>fraserus</N>
<N>big_juicy_cake</N>
<N>vintrel</N>
<N>idontcare</N>
<N>technocratic_pragmatists</N>
<N>aisle_of_union_gulf</N>
<N>jatiwaringin</N>
<N>saint_pinole_ii</N>
<N>starcrest_united</N>
<N>usfeig2</N>
<N>saibotia</N>
<N>shambhalion</N>
<N>camadaland</N>
<N>hua-mulan</N>
<N>castroreale</N>
<N>dumbases</N>
<N>aevana</N>
<N>elon_musk_cat_girls_and_grok</N>
<N>notcommunist2</N>
<N>cheesecakeastan</N>
<N>enhisen</N>
<N>sincorp</N>
<N>drentor</N>
<N>dubois_county</N>
<N>magnus_imperium_atlanticum</N>
<N>sigma_pug_land</N>
<N>merpiana</N>
<N>the_infinite_federation</N>
<N>suvmia</N>
<N>peace_and_wars</N>
<N>resaza</N>
<N>ribilz</N>
<N>the_supreme_uncs</N>
<N>comia_noracon</N>
<N>skytasia</N>
<N>silver_lining_y</N>
<N>indo_states</N>
<N>zarbirea</N>
<N>preomithia</N>
<N>tpose</N>
<N>achias</N>
<N>chinese_republic_of_chad</N>
<N>arroneia</N>
<N>kopits</N>
<N>sacro_imperio_de_atalica</N>
<N>give_me_cash</N>
<N>united_states_of_devonta</N>
<N>northern_cheek</N>
<N>notormea</N>
<N>litchenstienen</N>
<N>tranver</N>
<N>east_wabbinge</N>
<N>apalatci</N>
<N>bareu</N>
<N>socialists_reformed</N>
<N>smoky_oak</N>
<N>the_doomsday_islands</N>
<N>etemlju</N>
<N>hai_dao</N>
<N>zennit</N>
<N>united_states_of_camerica</N>
<N>north_caldwell</N>
<N>milestone_iv_guest_1337</N>
<N>qyra</N>
<N>ancient_slobovia</N>
<N>i_couldnt_come_up_with_a_name</N>
<N>greater_theowherveld</N>
<N>the_new_age_empire</N>
<N>mesozoic</N>
<N>pan_turkish_nation</N>
<N>pacificean</N>
<N>free_transhumanists</N>
<N>the_pacific_enclave</N>
<N>federated_commonwealth_of_selstville</N>
<N>5scheidten_beach</N>
<N>wisea</N>
<N>mearkuchozhativu</N>
<N>ihatetheusa</N>
<N>noo_de_plak</N>
<N>haykeren</N>
<N>wess_bribedoreadomia</N>
<N>nhoor</N>
<N>vikendia</N>
<N>socialist_republic_of_sakat</N>
<N>kyldania</N>
<N>azurth</N>
<N>federal_of_velmoria</N>
<N>luminerra</N>
<N>the_spire_of_shadows</N>
<N>yilfostera</N>
<N>byzantiium</N>
<N>cavernon</N>
<N>fales_dieska</N>
<N>the_new_california_republic</N>
<N>claires_metropolis</N>
<N>awful_country_to_live_in</N>
<N>molotossia</N>
<N>the_monolopem</N>
<N>the_architect_imperium</N>
<N>ordent_ratland</N>
<N>western_rhomania</N>
<N>landlocked_countries</N>
<N>9005</N>
<N>the_magicianss</N></VOTES_FOR>
</RESOLUTION>
</WA>
